{
  "item-states": [
    {
      "folded": false,
      "id": "3cmkqUkWlIhJXsnyaa+T0S"
    },
    {
      "folded": false,
      "id": "c35OuJc7xKeoLwWP9D2uM2"
    },
    {
      "folded": false,
      "id": "d9o8DHE+pI4IyjmgS3ZUVG"
    },
    {
      "folded": false,
      "id": "cblp7mkb9PBogsA8d+N0lt"
    },
    {
      "folded": false,
      "id": "6bVOlEi9hLp7sPhVBcjfXu"
    },
    {
      "folded": false,
      "id": "be2QJTmGBLgbuB+Dcl6p9F"
    },
    {
      "folded": false,
      "id": "8at/JR6DBFp6FChDuNnMdf"
    },
    {
      "folded": false,
      "id": "76jwwmjm1MiYlNecYWOMr1"
    }
  ]
}