{
  "appKey": "",
  "appSecret": "",
  "encryptJs": true,
  "excludeScenes": [],
  "fb-instant-games": {},
  "includeAnySDK": false,
  "includeSDKBox": false,
  "inlineSpriteFrames": true,
  "inlineSpriteFrames_native": true,
  "jailbreakPlatform": false,
  "md5Cache": true,
  "mergeStartScene": false,
  "oauthLoginServer": "",
  "optimizeHotUpdate": false,
  "orientation": {
    "landscapeLeft": true,
    "landscapeRight": true,
    "portrait": false,
    "upsideDown": false
  },
  "packageName": "org.cocos2d.NumberGame",
  "privateKey": "",
  "qqplay": {
    "REMOTE_SERVER_ROOT": "",
    "orientation": "portrait"
  },
  "renderMode": "0",
  "startScene": "3b636ea2-3877-49f8-8bee-c8adae90c48f",
  "title": "Number1aGame",
  "webOrientation": "auto",
  "wechatgame": {
    "REMOTE_SERVER_ROOT": "",
    "appid": "wx6ac3f5090a6b99c5",
    "isSubdomain": false,
    "orientation": "landscape",
    "subContext": ""
  },
  "xxteaKey": "bda21809-4d01-4c",
  "zipCompressJs": true
}